{
  "project_info": {
    "project_number": "964122832681",
    "firebase_url": "https://utsc-cscb07-project-2024-fall-default-rtdb.firebaseio.com",
    "project_id": "utsc-cscb07-project-2024-fall",
    "storage_bucket": "utsc-cscb07-project-2024-fall.firebasestorage.app"
  },
  "client": [
    {
      "client_info": {
        "mobilesdk_app_id": "1:964122832681:android:7ce2c4b686407ce4c25138",
        "android_client_info": {
          "package_name": "com.example.planetz"
        }
      },
      "oauth_client": [],
      "api_key": [
        {
          "current_key": "AIzaSyDfAK6hapxkUnZzCoQKAavphSQR12GNc4I"
        }
      ],
      "services": {
        "appinvite_service": {
          "other_platform_oauth_client": []
        }
      }
    }
  ],
  "configuration_version": "1"
}
